Workbook

Sheet Dashboard
A1: PERSONAL FINANCE DASHBOARD
A2: Your money at a glance. All numbers update automatically.
A4: TOTAL INCOME | E4: TOTAL EXPENSES | H4: TOTAL SAVINGS | K4: NET BALANCE
A5: ='Monthly Tracker'!O11 -> 17230 | D5: ='Monthly Tracker'!O28 -> 9215 | E5: ='Monthly Tracker'!O22 -> 80 | G5: ='Monthly Tracker'!O35 -> 2450 | H5: ='Monthly Tracker'!O28 -> 9215 | J5: ='Monthly Tracker'!O11-'Monthly Tracker'!O28-'Monthly Tracker'!O35 -> 5565 | K5: ='Monthly Tracker'!O6-'Monthly Tracker'!O22-'Monthly Tracker'!O28 -> 5705
A7: MONTHLY BREAKDOWN
A8: Month | B8: Income | C8: Expenses | D8: Savings | E8: Net Balance | F8: Savings Rate
A9: Jan | B9: ='Monthly Tracker'!C11 -> 5600 | C9: ='Monthly Tracker'!C28 -> 3030 | D9: ='Monthly Tracker'!C35 -> 800 | E9: =B9-C9-D9 -> 1770 | F9: =IF(B9=0,0,D9/B9) -> 0.14285714
A10: Feb | B10: ='Monthly Tracker'!D11 -> 5920 | C10: ='Monthly Tracker'!D28 -> 3190 | D10: ='Monthly Tracker'!D35 -> 850 | E10: =B10-C10-D10 -> 1880 | F10: =IF(B10=0,0,D10/B10) -> 0.14358108
A11: Mar | B11: ='Monthly Tracker'!E11 -> 5710 | C11: ='Monthly Tracker'!E28 -> 2995 | D11: ='Monthly Tracker'!E35 -> 800 | E11: =B11-C11-D11 -> 1915 | F11: =IF(B11=0,0,D11/B11) -> 0.14010508
A12: Apr | B12: ='Monthly Tracker'!F11 -> 0 | C12: ='Monthly Tracker'!F28 -> 0 | D12: ='Monthly Tracker'!F35 -> 0 | E12: =B12-C12-D12 -> 0 | F12: =IF(B12=0,0,D12/B12) -> 0
A13: May | B13: ='Monthly Tracker'!G11 -> 0 | C13: ='Monthly Tracker'!G28 -> 0 | D13: ='Monthly Tracker'!G35 -> 0 | E13: =B13-C13-D13 -> 0 | F13: =IF(B13=0,0,D13/B13) -> 0
A14: Jun | B14: ='Monthly Tracker'!H11 -> 0 | C14: ='Monthly Tracker'!H28 -> 0 | D14: ='Monthly Tracker'!H35 -> 0 | E14: =B14-C14-D14 -> 0 | F14: =IF(B14=0,0,D14/B14) -> 0
A15: Jul | B15: ='Monthly Tracker'!I11 -> 0 | C15: ='Monthly Tracker'!I28 -> 0 | D15: ='Monthly Tracker'!I35 -> 0 | E15: =B15-C15-D15 -> 0 | F15: =IF(B15=0,0,D15/B15) -> 0
A16: Aug | B16: ='Monthly Tracker'!J11 -> 0 | C16: ='Monthly Tracker'!J28 -> 0 | D16: ='Monthly Tracker'!J35 -> 0 | E16: =B16-C16-D16 -> 0 | F16: =IF(B16=0,0,D16/B16) -> 0
A17: Sep | B17: ='Monthly Tracker'!K11 -> 0 | C17: ='Monthly Tracker'!K28 -> 0 | D17: ='Monthly Tracker'!K35 -> 0 | E17: =B17-C17-D17 -> 0 | F17: =IF(B17=0,0,D17/B17) -> 0
A18: Oct | B18: ='Monthly Tracker'!L11 -> 0 | C18: ='Monthly Tracker'!L28 -> 0 | D18: ='Monthly Tracker'!L35 -> 0 | E18: =B18-C18-D18 -> 0 | F18: =IF(B18=0,0,D18/B18) -> 0
A19: Nov | B19: ='Monthly Tracker'!M11 -> 0 | C19: ='Monthly Tracker'!M28 -> 0 | D19: ='Monthly Tracker'!M35 -> 0 | E19: =B19-C19-D19 -> 0 | F19: =IF(B19=0,0,D19/B19) -> 0
A20: Dec | B20: ='Monthly Tracker'!N11 -> 0 | C20: ='Monthly Tracker'!N28 -> 0 | D20: ='Monthly Tracker'!N35 -> 0 | E20: =B20-C20-D20 -> 0 | F20: =IF(B20=0,0,D20/B20) -> 0
A21: ANNUAL TOTAL | B21: =SUM(B9:B20) -> 17230 | C21: =SUM(C9:C20) -> 9215 | D21: =SUM(D9:D20) -> 2450 | E21: =SUM(E9:E20) -> 5565 | F21: =SUM(F9:F20) -> 0.4265433

Sheet Monthly Tracker
A1: MONTHLY BUDGET TRACKER
A2: Blue cells = your input. Black cells = auto-calculated. Enter your numbers below.
A4: Category | B4: Type | C4: Jan | D4: Feb | E4: Mar | F4: Apr | G4: May | H4: Jun | I4: Jul | J4: Aug | K4: Sep | L4: Oct | M4: Nov | N4: Dec | O4: ANNUAL TOTAL
A5: INCOME
A6: Salary/Wages | B6: Income | C6: 5000 | D6: 5000 | E6: 5000 | O6: =SUM(C6:N6) -> 15000
A7: Freelance/Side Income | B7: Income | C7: 500 | D7: 800 | E7: 600 | O7: =SUM(C7:N7) -> 1900
A8: Investment Returns | B8: Income | C8: 100 | D8: 120 | E8: 110 | O8: =SUM(C8:N8) -> 330
A9: Rental Income | B9: Income | O9: =SUM(C9:N9) -> 0
A10: Other Income | B10: Income | O10: =SUM(C10:N10) -> 0
A11: TOTAL INCOME | C11: =SUM(C6:C10) -> 5600 | D11: =SUM(D6:D10) -> 5920 | E11: =SUM(E6:E10) -> 5710 | F11: =SUM(F6:F10) -> 0 | G11: =SUM(G6:G10) -> 0 | H11: =SUM(H6:H10) -> 0 | I11: =SUM(I6:I10) -> 0 | J11: =SUM(J6:J10) -> 0 | ... O11: =SUM(O6:O10) -> 17230
A12: EXPENSES
A13: Housing/Rent | B13: Expense | C13: 1500 | D13: 1500 | E13: 1500 | O13: =SUM(C13:N13) -> 4500
A14: Utilities (Electric, Water, Gas) | B14: Expense | C14: 200 | D14: 220 | E14: 190 | O14: =SUM(C14:N14) -> 610
A15: Groceries | B15: Expense | C15: 400 | D15: 450 | E15: 380 | O15: =SUM(C15:N15) -> 1230
A16: Transportation/Gas | B16: Expense | C16: 150 | D16: 160 | E16: 140 | O16: =SUM(C16:N16) -> 450
A17: Insurance (Health, Car, Home) | B17: Expense | C17: 300 | D17: 300 | E17: 300 | O17: =SUM(C17:N17) -> 900
A18: Phone/Internet | B18: Expense | C18: 120 | D18: 120 | E18: 120 | O18: =SUM(C18:N18) -> 360
A19: Dining Out/Restaurants | B19: Expense | C19: 200 | D19: 250 | E19: 180 | O19: =SUM(C19:N19) -> 630
A20: Entertainment/Subscriptions | B20: Expense | C20: 80 | D20: 90 | E20: 75 | O20: =SUM(C20:N20) -> 245
A21: Clothing/Personal Care | B21: Expense | C21: 50 | D21: 100 | E21: 60 | O21: =SUM(C21:N21) -> 210
A22: Medical/Healthcare | B22: Expense | C22: 30 | E22: 50 | O22: =SUM(C22:N22) -> 80
A23: Education/Learning | B23: Expense | O23: =SUM(C23:N23) -> 0
A24: Childcare/Family | B24: Expense | O24: =SUM(C24:N24) -> 0
A25: Home Maintenance | B25: Expense | O25: =SUM(C25:N25) -> 0
A26: Gifts/Donations | B26: Expense | O26: =SUM(C26:N26) -> 0
A27: Miscellaneous | B27: Expense | O27: =SUM(C27:N27) -> 0
A28: TOTAL EXPENSES | C28: =SUM(C13:C27) -> 3030 | D28: =SUM(D13:D27) -> 3190 | E28: =SUM(E13:E27) -> 2995 | F28: =SUM(F13:F27) -> 0 | G28: =SUM(G13:G27) -> 0 | H28: =SUM(H13:H27) -> 0 | I28: =SUM(I13:I27) -> 0 | J28: =SUM(J13:J27) -> 0 | ... O28: =SUM(O13:O27) -> 9215
A29: SAVINGS
A30: Emergency Fund | B30: Savings | C30: 200 | D30: 200 | E30: 200 | O30: =SUM(C30:N30) -> 600
A31: Retirement (401K/IRA) | B31: Savings | C31: 500 | D31: 500 | E31: 500 | O31: =SUM(C31:N31) -> 1500
A32: Investment Account | B32: Savings | C32: 100 | D32: 150 | E32: 100 | O32: =SUM(C32:N32) -> 350
A33: Vacation Fund | B33: Savings | O33: =SUM(C33:N33) -> 0
A34: Other Savings | B34: Savings | O34: =SUM(C34:N34) -> 0
A35: TOTAL SAVINGS | C35: =SUM(C30:C34) -> 800 | D35: =SUM(D30:D34) -> 850 | E35: =SUM(E30:E34) -> 800 | F35: =SUM(F30:F34) -> 0 | G35: =SUM(G30:G34) -> 0 | H35: =SUM(H30:H34) -> 0 | I35: =SUM(I30:I34) -> 0 | J35: =SUM(J30:J34) -> 0 | ... O35: =SUM(O30:O34) -> 2450
A36: NET BALANCE (Income minus Expenses minus Savings)
A37: NET BALANCE | C37: =C11-C28-C35 -> 1770 | D37: =D11-D28-D35 -> 1880 | E37: =E11-E28-E35 -> 1915 | F37: =F11-F28-F35 -> 0 | G37: =G11-G28-G35 -> 0 | H37: =H11-H28-H35 -> 0 | I37: =I11-I28-I35 -> 0 | J37: =J11-J28-J35 -> 0 | ... O37: =O11-O28-O35 -> 5565

Sheet Spending Insights
A1: SPENDING INSIGHTS
A2: See where your money goes. Find where to cut. Make smarter decisions.
A4: YOUR TOP 3 HIGHEST EXPENSES EACH MONTH
A5: Rank | B5: Jan | C5: Feb | D5: Mar | E5: Apr | F5: May | G5: Jun | H5: Jul | I5: Aug | J5: Sep | K5: Oct | L5: Nov | M5: Dec
A6: #1 Highest | B6: =IFERROR(LARGE('Monthly Tracker'!C13:C27,1),0) -> 1500 | C6: =IFERROR(LARGE('Monthly Tracker'!D13:D27,1),0) -> 1500 | D6: =IFERROR(LARGE('Monthly Tracker'!E13:E27,1),0) -> 1500 | E6: =IFERROR(LARGE('Monthly Tracker'!F13:F27,1),0) -> 0 | F6: =IFERROR(LARGE('Monthly Tracker'!G13:G27,1),0) -> 0 | G6: =IFERROR(LARGE('Monthly Tracker'!H13:H27,1),0) -> 0 | H6: =IFERROR(LARGE('Monthly Tracker'!I13:I27,1),0) -> 0 | I6: =IFERROR(LARGE('Monthly Tracker'!J13:J27,1),0) -> 0 | ... M6: =IFERROR(LARGE('Monthly Tracker'!N13:N27,1),0) -> 0
A7: #2 Highest | B7: =IFERROR(LARGE('Monthly Tracker'!C13:C27,2),0) -> 400 | C7: =IFERROR(LARGE('Monthly Tracker'!D13:D27,2),0) -> 450 | D7: =IFERROR(LARGE('Monthly Tracker'!E13:E27,2),0) -> 380 | E7: =IFERROR(LARGE('Monthly Tracker'!F13:F27,2),0) -> 0 | F7: =IFERROR(LARGE('Monthly Tracker'!G13:G27,2),0) -> 0 | G7: =IFERROR(LARGE('Monthly Tracker'!H13:H27,2),0) -> 0 | H7: =IFERROR(LARGE('Monthly Tracker'!I13:I27,2),0) -> 0 | I7: =IFERROR(LARGE('Monthly Tracker'!J13:J27,2),0) -> 0 | ... M7: =IFERROR(LARGE('Monthly Tracker'!N13:N27,2),0) -> 0
A8: #3 Highest | B8: =IFERROR(LARGE('Monthly Tracker'!C13:C27,3),0) -> 300 | C8: =IFERROR(LARGE('Monthly Tracker'!D13:D27,3),0) -> 300 | D8: =IFERROR(LARGE('Monthly Tracker'!E13:E27,3),0) -> 300 | E8: =IFERROR(LARGE('Monthly Tracker'!F13:F27,3),0) -> 0 | F8: =IFERROR(LARGE('Monthly Tracker'!G13:G27,3),0) -> 0 | G8: =IFERROR(LARGE('Monthly Tracker'!H13:H27,3),0) -> 0 | H8: =IFERROR(LARGE('Monthly Tracker'!I13:I27,3),0) -> 0 | I8: =IFERROR(LARGE('Monthly Tracker'!J13:J27,3),0) -> 0 | ... M8: =IFERROR(LARGE('Monthly Tracker'!N13:N27,3),0) -> 0
A10: WHAT CATEGORY IS COSTING YOU THE MOST?
A11: Insight | B11: Jan | C11: Feb | D11: Mar | E11: Apr | F11: May | G11: Jun | H11: Jul | I11: Aug | J11: Sep | K11: Oct | L11: Nov | M11: Dec
A12: Highest Expense Category | B12: =IFERROR(INDEX('Monthly Tracker'!$A$13:$A$27,MATCH(MAX('Monthly Tracker'!C13:C27),'Monthly Tracker'!C13:C27,0)),"No data") -> Housing/Rent | C12: =IFERROR(INDEX('Monthly Tracker'!$A$13:$A$27,MATCH(MAX('Monthly Tracker'!D13:D27),'Monthly Tracker'!D13:D27,0)),"No data") -> Housing/Rent | D12: =IFERROR(INDEX('Monthly Tracker'!$A$13:$A$27,MATCH(MAX('Monthly Tracker'!E13:E27),'Monthly Tracker'!E13:E27,0)),"No data") -> Housing/Rent | E12: =IFERROR(INDEX('Monthly Tracker'!$A$13:$A$27,MATCH(MAX('Monthly Tracker'!F13:F27),'Monthly Tracker'!F13:F27,0)),"No data") -> No data | F12: =IFERROR(INDEX('Monthly Tracker'!$A$13:$A$27,MATCH(MAX('Monthly Tracker'!G13:G27),'Monthly Tracker'!G13:G27,0)),"No data") -> No data | G12: =IFERROR(INDEX('Monthly Tracker'!$A$13:$A$27,MATCH(MAX('Monthly Tracker'!H13:H27),'Monthly Tracker'!H13:H27,0)),"No data") -> No data | H12: =IFERROR(INDEX('Monthly Tracker'!$A$13:$A$27,MATCH(MAX('Monthly Tracker'!I13:I27),'Monthly Tracker'!I13:I27,0)),"No data") -> No data | I12: =IFERROR(INDEX('Monthly Tracker'!$A$13:$A$27,MATCH(MAX('Monthly Tracker'!J13:J27),'Monthly Tracker'!J13:J27,0)),"No data") -> No data | ... M12: =IFERROR(INDEX('Monthly Tracker'!$A$13:$A$27,MATCH(MAX('Monthly Tracker'!N13:N27),'Monthly Tracker'!N13:N27,0)),"No data") -> No data
A13: Amount Spent | B13: =IFERROR(MAX('Monthly Tracker'!C13:C27),0) -> 1500 | C13: =IFERROR(MAX('Monthly Tracker'!D13:D27),0) -> 1500 | D13: =IFERROR(MAX('Monthly Tracker'!E13:E27),0) -> 1500 | E13: =IFERROR(MAX('Monthly Tracker'!F13:F27),0) -> 0 | F13: =IFERROR(MAX('Monthly Tracker'!G13:G27),0) -> 0 | G13: =IFERROR(MAX('Monthly Tracker'!H13:H27),0) -> 0 | H13: =IFERROR(MAX('Monthly Tracker'!I13:I27),0) -> 0 | I13: =IFERROR(MAX('Monthly Tracker'!J13:J27),0) -> 0 | ... M13: =IFERROR(MAX('Monthly Tracker'!N13:N27),0) -> 0
A14: % of Total Expenses | B14: =IFERROR(IF('Monthly Tracker'!C28=0,0,MAX('Monthly Tracker'!C13:C27)/'Monthly Tracker'!C28),0) -> 0.4950495 | C14: =IFERROR(IF('Monthly Tracker'!D28=0,0,MAX('Monthly Tracker'!D13:D27)/'Monthly Tracker'!D28),0) -> 0.47021944 | D14: =IFERROR(IF('Monthly Tracker'!E28=0,0,MAX('Monthly Tracker'!E13:E27)/'Monthly Tracker'!E28),0) -> 0.50083472 | E14: =IFERROR(IF('Monthly Tracker'!F28=0,0,MAX('Monthly Tracker'!F13:F27)/'Monthly Tracker'!F28),0) -> 0 | F14: =IFERROR(IF('Monthly Tracker'!G28=0,0,MAX('Monthly Tracker'!G13:G27)/'Monthly Tracker'!G28),0) -> 0 | G14: =IFERROR(IF('Monthly Tracker'!H28=0,0,MAX('Monthly Tracker'!H13:H27)/'Monthly Tracker'!H28),0) -> 0 | H14: =IFERROR(IF('Monthly Tracker'!I28=0,0,MAX('Monthly Tracker'!I13:I27)/'Monthly Tracker'!I28),0) -> 0 | I14: =IFERROR(IF('Monthly Tracker'!J28=0,0,MAX('Monthly Tracker'!J13:J27)/'Monthly Tracker'!J28),0) -> 0 | ... M14: =IFERROR(IF('Monthly Tracker'!N28=0,0,MAX('Monthly Tracker'!N13:N27)/'Monthly Tracker'!N28),0) -> 0
A16: ARE YOUR EXPENSES GOING UP OR DOWN? (Month over Month Change)
A17: Metric | B17: Jan | C17: Feb | D17: Mar | E17: Apr | F17: May | G17: Jun | H17: Jul | I17: Aug | J17: Sep | K17: Oct | L17: Nov | M17: Dec
A18: Total Expense Change ($) | B18: N/A | C18: ='Monthly Tracker'!D28-'Monthly Tracker'!C28 -> 160 | D18: ='Monthly Tracker'!E28-'Monthly Tracker'!D28 -> -195 | E18: ='Monthly Tracker'!F28-'Monthly Tracker'!E28 -> -2995 | F18: ='Monthly Tracker'!G28-'Monthly Tracker'!F28 -> 0 | G18: ='Monthly Tracker'!H28-'Monthly Tracker'!G28 -> 0 | H18: ='Monthly Tracker'!I28-'Monthly Tracker'!H28 -> 0 | I18: ='Monthly Tracker'!J28-'Monthly Tracker'!I28 -> 0 | J18: ='Monthly Tracker'!K28-'Monthly Tracker'!J28 -> 0 | ... M18: ='Monthly Tracker'!N28-'Monthly Tracker'!M28 -> 0
A19: Change (%) | B19: N/A | C19: =IF('Monthly Tracker'!C28=0,0,('Monthly Tracker'!D28-'Monthly Tracker'!C28)/'Monthly Tracker'!C28) -> 0.052805281 | D19: =IF('Monthly Tracker'!D28=0,0,('Monthly Tracker'!E28-'Monthly Tracker'!D28)/'Monthly Tracker'!D28) -> -0.061128527 | E19: =IF('Monthly Tracker'!E28=0,0,('Monthly Tracker'!F28-'Monthly Tracker'!E28)/'Monthly Tracker'!E28) -> -1 | F19: =IF('Monthly Tracker'!F28=0,0,('Monthly Tracker'!G28-'Monthly Tracker'!F28)/'Monthly Tracker'!F28) -> 0 | G19: =IF('Monthly Tracker'!G28=0,0,('Monthly Tracker'!H28-'Monthly Tracker'!G28)/'Monthly Tracker'!G28) -> 0 | H19: =IF('Monthly Tracker'!H28=0,0,('Monthly Tracker'!I28-'Monthly Tracker'!H28)/'Monthly Tracker'!H28) -> 0 | I19: =IF('Monthly Tracker'!I28=0,0,('Monthly Tracker'!J28-'Monthly Tracker'!I28)/'Monthly Tracker'!I28) -> 0 | J19: =IF('Monthly Tracker'!J28=0,0,('Monthly Tracker'!K28-'Monthly Tracker'!J28)/'Monthly Tracker'!J28) -> 0 | ... M19: =IF('Monthly Tracker'!M28=0,0,('Monthly Tracker'!N28-'Monthly Tracker'!M28)/'Monthly Tracker'!M28) -> 0
A20: Verdict | B20: N/A | C20: =IF('Monthly Tracker'!D28>'Monthly Tracker'!C28,"SPENDING UP","SPENDING DOWN") -> SPENDING UP | D20: =IF('Monthly Tracker'!E28>'Monthly Tracker'!D28,"SPENDING UP","SPENDING DOWN") -> SPENDING DOWN | E20: =IF('Monthly Tracker'!F28>'Monthly Tracker'!E28,"SPENDING UP","SPENDING DOWN") -> SPENDING DOWN | F20: =IF('Monthly Tracker'!G28>'Monthly Tracker'!F28,"SPENDING UP","SPENDING DOWN") -> SPENDING DOWN | G20: =IF('Monthly Tracker'!H28>'Monthly Tracker'!G28,"SPENDING UP","SPENDING DOWN") -> SPENDING DOWN | H20: =IF('Monthly Tracker'!I28>'Monthly Tracker'!H28,"SPENDING UP","SPENDING DOWN") -> SPENDING DOWN | I20: =IF('Monthly Tracker'!J28>'Monthly Tracker'!I28,"SPENDING UP","SPENDING DOWN") -> SPENDING DOWN | J20: =IF('Monthly Tracker'!K28>'Monthly Tracker'!J28,"SPENDING UP","SPENDING DOWN") -> SPENDING DOWN | ... M20: =IF('Monthly Tracker'!N28>'Monthly Tracker'!M28,"SPENDING UP","SPENDING DOWN") -> SPENDING DOWN
A22: WHERE TO REDUCE: YOUR ANNUAL EXPENSE BREAKDOWN (Sorted by Amount)
A23: Expense Category | B23: Annual Total | C23: % of All Expenses | D23: Monthly Average | E23: Recommendation
A24: Housing/Rent | B24: ='Monthly Tracker'!O13 -> 4500 | C24: =IF('Monthly Tracker'!O28=0,0,B24/'Monthly Tracker'!O28) -> 0.48833424 | D24: =IF(COUNTA('Monthly Tracker'!C13:N13)=0,0,B24/COUNTA('Monthly Tracker'!C13:N13)) -> 1500 | E24: =IF(C24>0.2,"HIGH: Major expense. Review for savings.",IF(C24>0.1,"MODERATE: Look for ways to trim.",IF(C24>0.05,"WATCH: Small but adds up over time.","OK: Reasonable spending."))) -> HIGH: Major expense. Review for savings.
A25: Utilities (Electric, Water, Gas) | B25: ='Monthly Tracker'!O14 -> 610 | C25: =IF('Monthly Tracker'!O28=0,0,B25/'Monthly Tracker'!O28) -> 0.066196419 | D25: =IF(COUNTA('Monthly Tracker'!C14:N14)=0,0,B25/COUNTA('Monthly Tracker'!C14:N14)) -> 203.33333 | E25: =IF(C25>0.2,"HIGH: Major expense. Review for savings.",IF(C25>0.1,"MODERATE: Look for ways to trim.",IF(C25>0.05,"WATCH: Small but adds up over time.","OK: Reasonable spending."))) -> WATCH: Small but adds up over time.
A26: Groceries | B26: ='Monthly Tracker'!O15 -> 1230 | C26: =IF('Monthly Tracker'!O28=0,0,B26/'Monthly Tracker'!O28) -> 0.13347802 | D26: =IF(COUNTA('Monthly Tracker'!C15:N15)=0,0,B26/COUNTA('Monthly Tracker'!C15:N15)) -> 410 | E26: =IF(C26>0.2,"HIGH: Major expense. Review for savings.",IF(C26>0.1,"MODERATE: Look for ways to trim.",IF(C26>0.05,"WATCH: Small but adds up over time.","OK: Reasonable spending."))) -> MODERATE: Look for ways to trim.
A27: Transportation/Gas | B27: ='Monthly Tracker'!O16 -> 450 | C27: =IF('Monthly Tracker'!O28=0,0,B27/'Monthly Tracker'!O28) -> 0.048833424 | D27: =IF(COUNTA('Monthly Tracker'!C16:N16)=0,0,B27/COUNTA('Monthly Tracker'!C16:N16)) -> 150 | E27: =IF(C27>0.2,"HIGH: Major expense. Review for savings.",IF(C27>0.1,"MODERATE: Look for ways to trim.",IF(C27>0.05,"WATCH: Small but adds up over time.","OK: Reasonable spending."))) -> OK: Reasonable spending.
A28: Insurance (Health, Car, Home) | B28: ='Monthly Tracker'!O17 -> 900 | C28: =IF('Monthly Tracker'!O28=0,0,B28/'Monthly Tracker'!O28) -> 0.097666848 | D28: =IF(COUNTA('Monthly Tracker'!C17:N17)=0,0,B28/COUNTA('Monthly Tracker'!C17:N17)) -> 300 | E28: =IF(C28>0.2,"HIGH: Major expense. Review for savings.",IF(C28>0.1,"MODERATE: Look for ways to trim.",IF(C28>0.05,"WATCH: Small but adds up over time.","OK: Reasonable spending."))) -> WATCH: Small but adds up over time.
A29: Phone/Internet | B29: ='Monthly Tracker'!O18 -> 360 | C29: =IF('Monthly Tracker'!O28=0,0,B29/'Monthly Tracker'!O28) -> 0.039066739 | D29: =IF(COUNTA('Monthly Tracker'!C18:N18)=0,0,B29/COUNTA('Monthly Tracker'!C18:N18)) -> 120 | E29: =IF(C29>0.2,"HIGH: Major expense. Review for savings.",IF(C29>0.1,"MODERATE: Look for ways to trim.",IF(C29>0.05,"WATCH: Small but adds up over time.","OK: Reasonable spending."))) -> OK: Reasonable spending.
A30: Dining Out/Restaurants | B30: ='Monthly Tracker'!O19 -> 630 | C30: =IF('Monthly Tracker'!O28=0,0,B30/'Monthly Tracker'!O28) -> 0.068366793 | D30: =IF(COUNTA('Monthly Tracker'!C19:N19)=0,0,B30/COUNTA('Monthly Tracker'!C19:N19)) -> 210 | E30: =IF(C30>0.2,"HIGH: Major expense. Review for savings.",IF(C30>0.1,"MODERATE: Look for ways to trim.",IF(C30>0.05,"WATCH: Small but adds up over time.","OK: Reasonable spending."))) -> WATCH: Small but adds up over time.
A31: Entertainment/Subscriptions | B31: ='Monthly Tracker'!O20 -> 245 | C31: =IF('Monthly Tracker'!O28=0,0,B31/'Monthly Tracker'!O28) -> 0.026587086 | D31: =IF(COUNTA('Monthly Tracker'!C20:N20)=0,0,B31/COUNTA('Monthly Tracker'!C20:N20)) -> 81.666667 | E31: =IF(C31>0.2,"HIGH: Major expense. Review for savings.",IF(C31>0.1,"MODERATE: Look for ways to trim.",IF(C31>0.05,"WATCH: Small but adds up over time.","OK: Reasonable spending."))) -> OK: Reasonable spending.
A32: Clothing/Personal Care | B32: ='Monthly Tracker'!O21 -> 210 | C32: =IF('Monthly Tracker'!O28=0,0,B32/'Monthly Tracker'!O28) -> 0.022788931 | D32: =IF(COUNTA('Monthly Tracker'!C21:N21)=0,0,B32/COUNTA('Monthly Tracker'!C21:N21)) -> 70 | E32: =IF(C32>0.2,"HIGH: Major expense. Review for savings.",IF(C32>0.1,"MODERATE: Look for ways to trim.",IF(C32>0.05,"WATCH: Small but adds up over time.","OK: Reasonable spending."))) -> OK: Reasonable spending.
A33: Medical/Healthcare | B33: ='Monthly Tracker'!O22 -> 80 | C33: =IF('Monthly Tracker'!O28=0,0,B33/'Monthly Tracker'!O28) -> 0.0086814976 | D33: =IF(COUNTA('Monthly Tracker'!C22:N22)=0,0,B33/COUNTA('Monthly Tracker'!C22:N22)) -> 40 | E33: =IF(C33>0.2,"HIGH: Major expense. Review for savings.",IF(C33>0.1,"MODERATE: Look for ways to trim.",IF(C33>0.05,"WATCH: Small but adds up over time.","OK: Reasonable spending."))) -> OK: Reasonable spending.
A34: Education/Learning | B34: ='Monthly Tracker'!O23 -> 0 | C34: =IF('Monthly Tracker'!O28=0,0,B34/'Monthly Tracker'!O28) -> 0 | D34: =IF(COUNTA('Monthly Tracker'!C23:N23)=0,0,B34/COUNTA('Monthly Tracker'!C23:N23)) -> 0 | E34: =IF(C34>0.2,"HIGH: Major expense. Review for savings.",IF(C34>0.1,"MODERATE: Look for ways to trim.",IF(C34>0.05,"WATCH: Small but adds up over time.","OK: Reasonable spending."))) -> OK: Reasonable spending.
A35: Childcare/Family | B35: ='Monthly Tracker'!O24 -> 0 | C35: =IF('Monthly Tracker'!O28=0,0,B35/'Monthly Tracker'!O28) -> 0 | D35: =IF(COUNTA('Monthly Tracker'!C24:N24)=0,0,B35/COUNTA('Monthly Tracker'!C24:N24)) -> 0 | E35: =IF(C35>0.2,"HIGH: Major expense. Review for savings.",IF(C35>0.1,"MODERATE: Look for ways to trim.",IF(C35>0.05,"WATCH: Small but adds up over time.","OK: Reasonable spending."))) -> OK: Reasonable spending.
A36: Home Maintenance | B36: ='Monthly Tracker'!O25 -> 0 | C36: =IF('Monthly Tracker'!O28=0,0,B36/'Monthly Tracker'!O28) -> 0 | D36: =IF(COUNTA('Monthly Tracker'!C25:N25)=0,0,B36/COUNTA('Monthly Tracker'!C25:N25)) -> 0 | E36: =IF(C36>0.2,"HIGH: Major expense. Review for savings.",IF(C36>0.1,"MODERATE: Look for ways to trim.",IF(C36>0.05,"WATCH: Small but adds up over time.","OK: Reasonable spending."))) -> OK: Reasonable spending.
A37: Gifts/Donations | B37: ='Monthly Tracker'!O26 -> 0 | C37: =IF('Monthly Tracker'!O28=0,0,B37/'Monthly Tracker'!O28) -> 0 | D37: =IF(COUNTA('Monthly Tracker'!C26:N26)=0,0,B37/COUNTA('Monthly Tracker'!C26:N26)) -> 0 | E37: =IF(C37>0.2,"HIGH: Major expense. Review for savings.",IF(C37>0.1,"MODERATE: Look for ways to trim.",IF(C37>0.05,"WATCH: Small but adds up over time.","OK: Reasonable spending."))) -> OK: Reasonable spending.
A38: Miscellaneous | B38: ='Monthly Tracker'!O27 -> 0 | C38: =IF('Monthly Tracker'!O28=0,0,B38/'Monthly Tracker'!O28) -> 0 | D38: =IF(COUNTA('Monthly Tracker'!C27:N27)=0,0,B38/COUNTA('Monthly Tracker'!C27:N27)) -> 0 | E38: =IF(C38>0.2,"HIGH: Major expense. Review for savings.",IF(C38>0.1,"MODERATE: Look for ways to trim.",IF(C38>0.05,"WATCH: Small but adds up over time.","OK: Reasonable spending."))) -> OK: Reasonable spending.

Sheet How To Use
A1: PERSONAL FINANCE BUDGET TRACKER 2026 - Vasuki
A2: How to Use This Template
A4: STEP 1: Go to the Monthly Tracker tab
A5: Enter your monthly income, expenses, and savings in the blue-colored cells. Each row is a category, each column is a month.
A6: Sample data is included for Jan through Mar so you can see how it works. Replace it with your own numbers.
A8: STEP 2: Check the Dashboard
A9: The Dashboard updates automatically. You'll see your total income, expenses, savings, and net balance at a glance.
A10: Charts show your income vs expenses trend, net balance trend, and savings rate over time.
A12: STEP 3: Check the Spending Insights tab (NEW!)
A13: This is where the real magic happens. The Spending Insights tab automatically tells you:
A14: • Your top 3 highest expenses each month
A15: • Which category is costing you the most (and what % of your total expenses)
... A28: Created by Vasuki Balasubramanian | vasukib31@gmail.com
